<news>
<time>2017-09-05-23-21-24-486</time>
<eugene>
<headline>Evacuation threat heightened for upper McKenzie River area - The Register-Guard</headline>
<headline>Wildfires across Oregon leave a cloak of smoke - The Register-Guard</headline>
<headline>Eugene Emeralds playoff game postponed until Wednesday - The Register-Guard</headline>
<headline>Danger in the Willamette Valley air - The Register-Guard</headline>
<headline>Most Oregon politicians, educators oppose DACA 'wind down' - The Register-Guard</headline>
</eugene>
<us>
<headline>Allies for 67 Years, US and South Korea Split Over North Korea - New York Times</headline>
<headline>Trump Moves to End DACA and Calls on Congress to Act - New York Times</headline>
<headline>Hurricane Irma to track toward US; Residents of East and Gulf coasts urged to prepare now - AccuWeather.com</headline>
<headline>Hurricane Harvey – We are the United States of America - Sonoran News</headline>
<headline>History shows us how calamitous the North Korea crisis could become - Washington Post</headline>
</us>
<world>
<headline>Socceroos must face Syria in World Cup play-off as Saudi Arabia take finals spot - The Guardian</headline>
<headline>Plastic fibres found in tap water around the world, study reveals - The Guardian</headline>
<headline>Review: In 'Spettacolo,' a Tuscan Town Where All the World's a Stage - New York Times</headline>
<headline>Gordi On World Cafe : World Cafe : NPR - NPR</headline>
<headline>Google's New Street View Cameras Will Help Algorithms Index The ... - WIRED</headline>
</world>
</news>
<message type="test">
<time>2017-09-05-23-21-31-456</time>
<word>deaf</word>
</message>
<message type="test">
<time>2017-09-05-23-22-45-415</time>
<word>enraged</word>
</message>
<message type="auto">
<time>2017-09-06-00-59-37-467</time>
<word>dumb</word>
</message>
<message type="auto">
<time>2017-09-06-02-24-59-855</time>
<word>sleeps</word>
</message>
<message type="auto">
<time>2017-09-06-02-36-11-755</time>
<word>loves</word>
</message>
<message type="auto">
<time>2017-09-06-03-14-25-715</time>
<word>sleeps</word>
</message>
<message type="auto">
<time>2017-09-06-04-00-53-932</time>
<word>person</word>
</message>
<message type="auto">
<time>2017-09-06-04-05-32-284</time>
<word>female</word>
</message>
<message type="auto">
<time>2017-09-06-04-18-27-701</time>
<word>prisoner</word>
</message>
<message type="auto">
<time>2017-09-06-04-42-53-980</time>
<word>son</word>
</message>
<message type="auto">
<time>2017-09-06-04-43-52-097</time>
<word>female</word>
</message>
<message type="auto">
<time>2017-09-06-06-51-53-647</time>
<word>dispositions</word>
</message>
<message type="auto">
<time>2017-09-06-06-52-05-624</time>
<word>treacherous</word>
</message>
<message type="auto">
<time>2017-09-06-06-55-40-344</time>
<word>prisoner</word>
</message>
<message type="auto">
<time>2017-09-06-07-16-08-902</time>
<word>money-maker</word>
</message>
<message type="auto">
<time>2017-09-06-08-53-36-932</time>
<word>dumb</word>
</message>
<message type="auto">
<time>2017-09-06-08-55-14-487</time>
<word>sleeps</word>
</message>
<message type="auto">
<time>2017-09-06-08-55-32-721</time>
<word>husband</word>
</message>
<message type="auto">
<time>2017-09-06-09-01-43-245</time>
<word>men</word>
</message>
<message type="auto">
<time>2017-09-06-09-14-57-016</time>
<word>dumb</word>
</message>
<message type="auto">
<time>2017-09-06-09-18-08-234</time>
<word>bed</word>
</message>
