<news>
<time>2017-10-08-00-14-17-729</time>
<eugene>
<headline>For the Record - The Register-Guard</headline>
<headline>Road Report - The Register-Guard</headline>
<headline>Around the region - The Register-Guard</headline>
<headline>Business datebook - The Register-Guard</headline>
<headline>The week's hot topics on the web - The Register-Guard</headline>
</eugene>
<us>
<headline>Joint Statement between the United States of America and the ... - The White House (blog)</headline>
<headline>Tensions Follow Rohingya Refugees to United States - Voice of America</headline>
<headline>Should the United States Celebrate Columbus Day? - New York Times</headline>
<headline>President Donald J. Trump Proclaims October 6, 2017, as German-American Day - The White House (blog)</headline>
<headline>President Donald J. Trump Proclaims October 8 through October 14, 2017, as Fire Prevention Week - The White House (blog)</headline>
</us>
<world>
<headline>Hurricane Nate makes landfall in Louisiana and Mississippi - BBC News</headline>
<headline>Belarus 1-3 Holland, Bulgaria 0-1 France: World Cup 2018 qualifiers – as it happened - The Guardian</headline>
<headline>Waston heroics lift Costa Rica into fifth World Cup - FIFA.com</headline>
<headline>Watch the Nintendo World Championships 2017 here - Polygon</headline>
<headline>Rouhani: World will condemn US if it quits nuclear deal - Aljazeera.com</headline>
</world>
</news>
<message type="test">
<time>2017-10-08-00-14-24-690</time>
<word>feet</word>
</message>
<message type="test">
<time>2017-10-08-00-14-33-307</time>
<word>white-features</word>
</message>
<message type="auto">
<time>2017-10-08-00-20-12-844</time>
<word>night</word>
</message>
<message type="auto">
<time>2017-10-08-01-03-39-532</time>
<word>pervades</word>
</message>
<message type="auto">
<time>2017-10-08-01-07-00-639</time>
<word>wrapt</word>
</message>
<message type="auto">
<time>2017-10-08-01-07-37-120</time>
<word>vision</word>
</message>
<message type="auto">
<time>2017-10-08-01-20-59-340</time>
<word>stoping</word>
</message>
<message type="auto">
<time>2017-10-08-01-38-04-651</time>
<word>men</word>
</message>
<message type="auto">
<time>2017-10-08-01-46-03-049</time>
<word>myself</word>
</message>
<message type="auto">
<time>2017-10-08-01-53-35-284</time>
<word>sisters</word>
</message>
<message type="auto">
<time>2017-10-08-02-11-02-324</time>
<word>vision</word>
</message>
<message type="auto">
<time>2017-10-08-02-48-21-390</time>
<word>stepping</word>
</message>
<message type="auto">
<time>2017-10-08-02-59-59-385</time>
<word>sacred-idiots</word>
</message>
<message type="auto">
<time>2017-10-08-03-05-06-924</time>
<word>men</word>
</message>
<message type="auto">
<time>2017-10-08-03-12-02-426</time>
<word>wonder</word>
</message>
<message type="auto">
<time>2017-10-08-03-22-19-792</time>
<word>pervades</word>
</message>
<message type="auto">
<time>2017-10-08-03-24-42-834</time>
<word>wrapt</word>
</message>
<message type="auto">
<time>2017-10-08-03-36-54-859</time>
<word>quiet</word>
</message>
<message type="auto">
<time>2017-10-08-04-02-37-651</time>
<word>white-features</word>
</message>
<message type="auto">
<time>2017-10-08-04-15-03-306</time>
<word>sisters</word>
</message>
<message type="auto">
<time>2017-10-08-04-39-29-103</time>
<word>strong-door</word>
</message>
<message type="auto">
<time>2017-10-08-04-50-45-793</time>
<word>white-features</word>
</message>
<message type="auto">
<time>2017-10-08-05-58-41-756</time>
<word>sacred-idiots</word>
</message>
<message type="auto">
<time>2017-10-08-06-15-41-537</time>
<word>stick-gray</word>
</message>
<message type="auto">
<time>2017-10-08-06-35-30-509</time>
<word>sacred-idiots</word>
</message>
<message type="auto">
<time>2017-10-08-06-37-01-993</time>
<word>side-by-side</word>
</message>
<message type="auto">
<time>2017-10-08-06-57-49-531</time>
<word>stretch</word>
</message>
<message type="auto">
<time>2017-10-08-07-21-59-030</time>
<word>side-by-side</word>
</message>
<message type="auto">
<time>2017-10-08-07-33-42-354</time>
<word>pausing</word>
</message>
<message type="auto">
<time>2017-10-08-07-45-39-546</time>
<word>mother</word>
</message>
<message type="auto">
<time>2017-10-08-07-52-45-947</time>
<word>stoping</word>
</message>
